pysurprisal/__init__.py
pysurprisal/core.py
pysurprisal-0.1.0.dist-info/LICENSE.md
pysurprisal-0.1.0.dist-info/METADATA
pysurprisal-0.1.0.dist-info/WHEEL
pysurprisal-0.1.0.dist-info/top_level.txt
pysurprisal-0.1.0.dist-info/RECORD
